MANIFEST.in
README.md
setup.py
currencyware/__init__.py
currencyware/admin.py
currencyware/apps.py
currencyware/currency.json
currencyware/currency.py
currencyware/defaults.py
currencyware/fields.py
currencyware/models.py
currencyware/utils.py
currencyware/__pycache__/__init__.cpython-36.pyc
currencyware/__pycache__/admin.cpython-36.pyc
currencyware/__pycache__/apps.cpython-36.pyc
currencyware/__pycache__/country.cpython-36.pyc
currencyware/__pycache__/currency.cpython-36.pyc
currencyware/__pycache__/defaults.cpython-36.pyc
currencyware/__pycache__/models.cpython-36.pyc
currencyware/__pycache__/utils.cpython-36.pyc
currencyware/locale/af/LC_MESSAGES/django.mo
currencyware/locale/af/LC_MESSAGES/django.po
currencyware/locale/am/LC_MESSAGES/django.mo
currencyware/locale/am/LC_MESSAGES/django.po
currencyware/locale/ar/LC_MESSAGES/django.mo
currencyware/locale/ar/LC_MESSAGES/django.po
currencyware/locale/as/LC_MESSAGES/django.mo
currencyware/locale/as/LC_MESSAGES/django.po
currencyware/locale/az/LC_MESSAGES/django.mo
currencyware/locale/az/LC_MESSAGES/django.po
currencyware/locale/be/LC_MESSAGES/django.mo
currencyware/locale/be/LC_MESSAGES/django.po
currencyware/locale/bg/LC_MESSAGES/django.mo
currencyware/locale/bg/LC_MESSAGES/django.po
currencyware/locale/bn/LC_MESSAGES/django.mo
currencyware/locale/bn/LC_MESSAGES/django.po
currencyware/locale/br/LC_MESSAGES/django.mo
currencyware/locale/br/LC_MESSAGES/django.po
currencyware/locale/bs/LC_MESSAGES/django.mo
currencyware/locale/bs/LC_MESSAGES/django.po
currencyware/locale/ca/LC_MESSAGES/django.mo
currencyware/locale/ca/LC_MESSAGES/django.po
currencyware/locale/cs/LC_MESSAGES/django.mo
currencyware/locale/cs/LC_MESSAGES/django.po
currencyware/locale/cy/LC_MESSAGES/django.mo
currencyware/locale/cy/LC_MESSAGES/django.po
currencyware/locale/da/LC_MESSAGES/django.mo
currencyware/locale/da/LC_MESSAGES/django.po
currencyware/locale/de/LC_MESSAGES/django.mo
currencyware/locale/de/LC_MESSAGES/django.po
django_currencyware.egg-info/PKG-INFO
django_currencyware.egg-info/SOURCES.txt
django_currencyware.egg-info/dependency_links.txt
django_currencyware.egg-info/requires.txt
django_currencyware.egg-info/top_level.txt